LICENSE
README.md
pyproject.toml
wamp/__init__.py
wamp/__main__.py
wamp/acceptor.py
wamp/app.py
wamp/client.py
wamp/helpers.py
wamp/joiner.py
wamp/realm.py
wamp/router.py
wamp/server.py
wamp/session.py
wamp/types.py
wamp.py.egg-info/PKG-INFO
wamp.py.egg-info/SOURCES.txt
wamp.py.egg-info/dependency_links.txt
wamp.py.egg-info/entry_points.txt
wamp.py.egg-info/requires.txt
wamp.py.egg-info/top_level.txt