Metadata-Version: 2.1
Name: wamp.py
Version: 0.1.0
Summary: https://github.com/xconnio/wamp.py
Author-email: Omer Akram <omer@thing.com>, Mahad Munir <mahad@xconn.io>
License: MIT License
Project-URL: Homepage, https://github.com/xconnio/wamp.py
Project-URL: Bug Tracker, https://github.com/xconnio/wamp.py/issues
Classifier: Development Status :: 4 - Beta
Classifier: License :: OSI Approved :: MIT License
Classifier: Programming Language :: Python :: 3.10
Classifier: Programming Language :: Python :: 3.11
Classifier: Programming Language :: Python :: 3.12
Requires-Python: >=3.10
License-File: LICENSE
Requires-Dist: websockets
Requires-Dist: wampproto
Requires-Dist: aiohttp
Requires-Dist: uvloop
Provides-Extra: test
Requires-Dist: coverage; extra == "test"
Requires-Dist: pytest; extra == "test"
Requires-Dist: pytest-asyncio; extra == "test"
Requires-Dist: ruff; extra == "test"
